geoutils/__init__.py
geoutils/_config.py
geoutils/_misc.py
geoutils/_typing.py
geoutils/_version.py
geoutils/config.ini
geoutils/examples.py
geoutils/filters.py
geoutils/profiler.py
geoutils/projtools.py
geoutils/interface/__init__.py
geoutils/interface/distance.py
geoutils/interface/gridding.py
geoutils/interface/interpolate.py
geoutils/interface/raster_point.py
geoutils/interface/raster_vector.py
geoutils/pointcloud/__init__.py
geoutils/pointcloud/pointcloud.py
geoutils/raster/__init__.py
geoutils/raster/_geotransformations.py
geoutils/raster/array.py
geoutils/raster/georeferencing.py
geoutils/raster/geotransformations.py
geoutils/raster/multiraster.py
geoutils/raster/raster.py
geoutils/raster/satimg.py
geoutils/raster/tiling.py
geoutils/raster/distributed_computing/__init__.py
geoutils/raster/distributed_computing/chunked.py
geoutils/raster/distributed_computing/cluster.py
geoutils/raster/distributed_computing/dask.py
geoutils/raster/distributed_computing/multiproc.py
geoutils/stats/__init__.py
geoutils/stats/estimators.py
geoutils/stats/sampling.py
geoutils/stats/stats.py
geoutils/vector/__init__.py
geoutils/vector/geometric.py
geoutils/vector/geotransformations.py
geoutils/vector/vector.py
geoutils-0.2.2.data/scripts/geoviewer.py
geoutils-0.2.2.dist-info/licenses/LICENSE
geoutils-0.2.2.dist-info/METADATA
geoutils-0.2.2.dist-info/WHEEL
geoutils-0.2.2.dist-info/top_level.txt
geoutils-0.2.2.dist-info/RECORD
