Metadata-Version: 2.4
Name: geoutils
Version: 0.2.2
Summary: Analysis of georeferenced rasters, vectors and point clouds
Home-page: https://github.com/GlacioHack/geoutils
Download-URL: https://pypi.org/project/geoutils/
Author: GeoUtils developers
License: Apache-2.0
Keywords: raster,vector,point,geospatial,gis,xarray,pandas
Platform: any
Classifier: Development Status :: 4 - Beta
Classifier: Intended Audience :: Developers
Classifier: Intended Audience :: Science/Research
Classifier: Natural Language :: English
Classifier: Operating System :: OS Independent
Classifier: Topic :: Scientific/Engineering :: GIS
Classifier: Topic :: Scientific/Engineering :: Image Processing
Classifier: Topic :: Scientific/Engineering :: Information Analysis
Classifier: Programming Language :: Python
Classifier: Programming Language :: Python :: 3.10
Classifier: Programming Language :: Python :: 3.11
Classifier: Programming Language :: Python :: 3.12
Classifier: Programming Language :: Python :: 3.13
Classifier: Programming Language :: Python :: 3
Classifier: Topic :: Software Development :: Libraries :: Python Modules
Classifier: Typing :: Typed
Requires-Python: <3.14,>=3.10
License-File: LICENSE
Requires-Dist: geopandas>=0.12.0
Requires-Dist: rasterio<1.4.4,>=1.3
Requires-Dist: scipy==1.*
Requires-Dist: xarray>2023
Requires-Dist: rioxarray==0.*
Requires-Dist: pyproj==3.*
Requires-Dist: pandas<3,>=1
Requires-Dist: numpy<3,>=1
Requires-Dist: affine
Requires-Dist: shapely
Requires-Dist: pyogrio
Provides-Extra: opt
Requires-Dist: laspy[lazrs]; extra == "opt"
Requires-Dist: numba; extra == "opt"
Requires-Dist: dask; extra == "opt"
Requires-Dist: matplotlib; extra == "opt"
Requires-Dist: psutil; extra == "opt"
Requires-Dist: plotly; extra == "opt"
Provides-Extra: test
Requires-Dist: gdal; extra == "test"
Requires-Dist: pytest<8,>=7; extra == "test"
Requires-Dist: pytest-xdist; extra == "test"
Requires-Dist: pytest-lazy-fixtures; extra == "test"
Requires-Dist: pytest-instafail; extra == "test"
Requires-Dist: pytest-socket; extra == "test"
Requires-Dist: pytest-cov; extra == "test"
Requires-Dist: coveralls; extra == "test"
Requires-Dist: pyyaml; extra == "test"
Requires-Dist: flake8; extra == "test"
Requires-Dist: netcdf4; extra == "test"
Requires-Dist: pre-commit; extra == "test"
Provides-Extra: doc
Requires-Dist: sphinx; extra == "doc"
Requires-Dist: sphinx-book-theme; extra == "doc"
Requires-Dist: sphinx-gallery; extra == "doc"
Requires-Dist: sphinx-design; extra == "doc"
Requires-Dist: sphinx-autodoc-typehints; extra == "doc"
Requires-Dist: sphinxcontrib-programoutput; extra == "doc"
Requires-Dist: sphinx-argparse; extra == "doc"
Requires-Dist: autovizwidget; extra == "doc"
Requires-Dist: graphviz; extra == "doc"
Requires-Dist: myst-nb; extra == "doc"
Requires-Dist: numpydoc; extra == "doc"
Requires-Dist: typing-extensions; extra == "doc"
Provides-Extra: dev
Requires-Dist: laspy[lazrs]; extra == "dev"
Requires-Dist: numba; extra == "dev"
Requires-Dist: dask; extra == "dev"
Requires-Dist: matplotlib; extra == "dev"
Requires-Dist: psutil; extra == "dev"
Requires-Dist: plotly; extra == "dev"
Requires-Dist: gdal; extra == "dev"
Requires-Dist: pytest<8,>=7; extra == "dev"
Requires-Dist: pytest-xdist; extra == "dev"
Requires-Dist: pytest-lazy-fixtures; extra == "dev"
Requires-Dist: pytest-instafail; extra == "dev"
Requires-Dist: pytest-socket; extra == "dev"
Requires-Dist: pytest-cov; extra == "dev"
Requires-Dist: coveralls; extra == "dev"
Requires-Dist: pyyaml; extra == "dev"
Requires-Dist: flake8; extra == "dev"
Requires-Dist: netcdf4; extra == "dev"
Requires-Dist: pre-commit; extra == "dev"
Requires-Dist: sphinx; extra == "dev"
Requires-Dist: sphinx-book-theme; extra == "dev"
Requires-Dist: sphinx-gallery; extra == "dev"
Requires-Dist: sphinx-design; extra == "dev"
Requires-Dist: sphinx-autodoc-typehints; extra == "dev"
Requires-Dist: sphinxcontrib-programoutput; extra == "dev"
Requires-Dist: sphinx-argparse; extra == "dev"
Requires-Dist: autovizwidget; extra == "dev"
Requires-Dist: graphviz; extra == "dev"
Requires-Dist: myst-nb; extra == "dev"
Requires-Dist: numpydoc; extra == "dev"
Requires-Dist: typing-extensions; extra == "dev"
Requires-Dist: psutil; extra == "dev"
Requires-Dist: plotly; extra == "dev"
Provides-Extra: all
Requires-Dist: laspy[lazrs]; extra == "all"
Requires-Dist: numba; extra == "all"
Requires-Dist: dask; extra == "all"
Requires-Dist: matplotlib; extra == "all"
Requires-Dist: psutil; extra == "all"
Requires-Dist: plotly; extra == "all"
Requires-Dist: gdal; extra == "all"
Requires-Dist: pytest<8,>=7; extra == "all"
Requires-Dist: pytest-xdist; extra == "all"
Requires-Dist: pytest-lazy-fixtures; extra == "all"
Requires-Dist: pytest-instafail; extra == "all"
Requires-Dist: pytest-socket; extra == "all"
Requires-Dist: pytest-cov; extra == "all"
Requires-Dist: coveralls; extra == "all"
Requires-Dist: pyyaml; extra == "all"
Requires-Dist: flake8; extra == "all"
Requires-Dist: netcdf4; extra == "all"
Requires-Dist: pre-commit; extra == "all"
Requires-Dist: sphinx; extra == "all"
Requires-Dist: sphinx-book-theme; extra == "all"
Requires-Dist: sphinx-gallery; extra == "all"
Requires-Dist: sphinx-design; extra == "all"
Requires-Dist: sphinx-autodoc-typehints; extra == "all"
Requires-Dist: sphinxcontrib-programoutput; extra == "all"
Requires-Dist: sphinx-argparse; extra == "all"
Requires-Dist: autovizwidget; extra == "all"
Requires-Dist: graphviz; extra == "all"
Requires-Dist: myst-nb; extra == "all"
Requires-Dist: numpydoc; extra == "all"
Requires-Dist: typing-extensions; extra == "all"
Requires-Dist: psutil; extra == "all"
Requires-Dist: plotly; extra == "all"
Dynamic: download-url
Dynamic: license-file
